ssm_secret_manager/__init__.py
ssm_secret_manager/main.py
ssm_secret_manager-0.1.1.dist-info/LICENSE
ssm_secret_manager-0.1.1.dist-info/METADATA
ssm_secret_manager-0.1.1.dist-info/WHEEL
ssm_secret_manager-0.1.1.dist-info/top_level.txt
ssm_secret_manager-0.1.1.dist-info/RECORD
