Metadata-Version: 2.1
Name: ssm-secret-manager
Version: 0.1.1
Summary: SecretManager class to retrieve secrets from AWS System Manager Parameter Store
Home-page: https://github.com/bklim5/aws-ssm-secret-manager
Author: BK Lim
Author-email: bklim5@hotmail.com
License: MIT
Keywords: secret manager,AWS,Parameter Store
Platform: UNKNOWN
Classifier: Programming Language :: Python :: 3
Classifier: License :: OSI Approved :: MIT License
Classifier: Operating System :: OS Independent
Requires-Dist: boto3
